awemecommit/__init__.py
awemecommit/commands/commit.py
awemecommit/commands/commit_config.py
awemecommit/commands/helper.py
awemecommit/commands/onecommit.py
awemecommit/main.py
awemecommit-0.7.0.dist-info/entry_points.txt
awemecommit-0.7.0.dist-info/WHEEL
awemecommit-0.7.0.dist-info/METADATA
awemecommit-0.7.0.dist-info/RECORD
