Metadata-Version: 2.1
Name: awemecommit
Version: 0.7.0
Summary: 
Author: Zijie Fang
Author-email: fangzijie.proalex@bytedance.com
Requires-Python: >=3.8,<4.0
Classifier: Programming Language :: Python :: 3
Classifier: Programming Language :: Python :: 3.10
Classifier: Programming Language :: Python :: 3.8
Classifier: Programming Language :: Python :: 3.9
Requires-Dist: GitPython (>=3.1.27,<4.0.0)
Requires-Dist: pyperclip (>=1.8.2,<2.0.0)
Requires-Dist: questionary (>=1.10.0,<2.0.0)
Requires-Dist: typer (>=0.4.1,<0.5.0)
